{
  "groups": [
    {
      "name": "coolsms",
      "type": "com.know_who_how.main_server.global.config.CoolSmsProperties",
      "sourceType": "com.know_who_how.main_server.global.config.CoolSmsProperties"
    },
    {
      "name": "jwt",
      "type": "com.know_who_how.main_server.global.jwt.JwtProperties",
      "sourceType": "com.know_who_how.main_server.global.jwt.JwtProperties"
    },
    {
      "name": "mydata",
      "type": "com.know_who_how.main_server.global.config.MydataProperties",
      "sourceType": "com.know_who_how.main_server.global.config.MydataProperties"
    },
    {
      "name": "mydata.as",
      "type": "com.know_who_how.main_server.global.config.MydataProperties$AsProperties",
      "sourceType": "com.know_who_how.main_server.global.config.MydataProperties",
      "sourceMethod": "public com.know_who_how.main_server.global.config.MydataProperties.AsProperties getAs() "
    },
    {
      "name": "mydata.rs",
      "type": "com.know_who_how.main_server.global.config.MydataProperties$RsProperties",
      "sourceType": "com.know_who_how.main_server.global.config.MydataProperties",
      "sourceMethod": "public com.know_who_how.main_server.global.config.MydataProperties.RsProperties getRs() "
    }
  ],
  "properties": [
    {
      "name": "coolsms.api-key",
      "type": "java.lang.String",
      "sourceType": "com.know_who_how.main_server.global.config.CoolSmsProperties"
    },
    {
      "name": "coolsms.api-secret",
      "type": "java.lang.String",
      "sourceType": "com.know_who_how.main_server.global.config.CoolSmsProperties"
    },
    {
      "name": "coolsms.from-number",
      "type": "java.lang.String",
      "sourceType": "com.know_who_how.main_server.global.config.CoolSmsProperties"
    },
    {
      "name": "jwt.access-token-validity-in-seconds",
      "type": "java.lang.Long",
      "sourceType": "com.know_who_how.main_server.global.jwt.JwtProperties"
    },
    {
      "name": "jwt.header",
      "type": "java.lang.String",
      "sourceType": "com.know_who_how.main_server.global.jwt.JwtProperties"
    },
    {
      "name": "jwt.refresh-secret",
      "type": "java.lang.String",
      "sourceType": "com.know_who_how.main_server.global.jwt.JwtProperties"
    },
    {
      "name": "jwt.refresh-token-validity-in-seconds",
      "type": "java.lang.Long",
      "sourceType": "com.know_who_how.main_server.global.jwt.JwtProperties"
    },
    {
      "name": "jwt.secret",
      "type": "java.lang.String",
      "sourceType": "com.know_who_how.main_server.global.jwt.JwtProperties"
    },
    {
      "name": "mydata.as.authorize-uri",
      "type": "java.lang.String",
      "sourceType": "com.know_who_how.main_server.global.config.MydataProperties$AsProperties"
    },
    {
      "name": "mydata.as.token-uri",
      "type": "java.lang.String",
      "sourceType": "com.know_who_how.main_server.global.config.MydataProperties$AsProperties"
    },
    {
      "name": "mydata.client-id",
      "type": "java.lang.String",
      "sourceType": "com.know_who_how.main_server.global.config.MydataProperties"
    },
    {
      "name": "mydata.client-secret",
      "type": "java.lang.String",
      "sourceType": "com.know_who_how.main_server.global.config.MydataProperties"
    },
    {
      "name": "mydata.redirect-uri",
      "type": "java.lang.String",
      "sourceType": "com.know_who_how.main_server.global.config.MydataProperties"
    },
    {
      "name": "mydata.rs.base-url",
      "type": "java.lang.String",
      "sourceType": "com.know_who_how.main_server.global.config.MydataProperties$RsProperties"
    }
  ],
  "hints": []
}